mdsuite/__init__.py
mdsuite/calculators/__init__.py
mdsuite/calculators/angular_distribution_function.py
mdsuite/calculators/calculator.py
mdsuite/calculators/coordination_number_calculation.py
mdsuite/calculators/einstein_diffusion_coefficients.py
mdsuite/calculators/einstein_distinct_diffusion_coefficients.py
mdsuite/calculators/einstein_helfand_ionic_conductivity.py
mdsuite/calculators/einstein_helfand_thermal_conductivity.py
mdsuite/calculators/einstein_helfand_thermal_kinaci.py
mdsuite/calculators/green_kubo_distinct_diffusion_coefficients.py
mdsuite/calculators/green_kubo_ionic_conductivity.py
mdsuite/calculators/green_kubo_self_diffusion_coefficients.py
mdsuite/calculators/green_kubo_thermal_conductivity.py
mdsuite/calculators/green_kubo_viscosity.py
mdsuite/calculators/green_kubo_viscosity_flux.py
mdsuite/calculators/kirkwood_buff_integrals.py
mdsuite/calculators/nernst_einstein_ionic_conductivity.py
mdsuite/calculators/potential_of_mean_force.py
mdsuite/calculators/radial_distribution_function.py
mdsuite/calculators/spatial_distribution_function.py
mdsuite/calculators/structure_factor.py
mdsuite/calculators/trajectory_calculator.py
mdsuite/calculators/transformations_reference.py
mdsuite/data/PubChemElements_all.json
mdsuite/data/__init__.py
mdsuite/data/form_fac_coeffs.csv
mdsuite/database/__init__.py
mdsuite/database/calculator_database.py
mdsuite/database/data_manager.py
mdsuite/database/database_base.py
mdsuite/database/experiment_database.py
mdsuite/database/mdsuite_properties.py
mdsuite/database/project_database.py
mdsuite/database/scheme.py
mdsuite/database/simulation_database.py
mdsuite/database/types.py
mdsuite/experiment/__init__.py
mdsuite/experiment/experiment.py
mdsuite/experiment/run.py
mdsuite/experiment/run_module.py
mdsuite/file_io/__init__.py
mdsuite/file_io/chemfiles_read.py
mdsuite/file_io/extxyz_files.py
mdsuite/file_io/file_read.py
mdsuite/file_io/lammps_flux_files.py
mdsuite/file_io/lammps_trajectory_files.py
MDSuite-0.2.0.dist-info/LICENSE
MDSuite-0.2.0.dist-info/METADATA
MDSuite-0.2.0.dist-info/WHEEL
MDSuite-0.2.0.dist-info/top_level.txt
MDSuite-0.2.0.dist-info/RECORD
