Metadata-Version: 2.1
Name: MDSuite
Version: 0.2.0
Summary: A postprocessing tool for molecular dynamics simulations.
Home-page: https://github.com/zincware/MDSuite
Author: zincwarecode
Author-email: zincwarecode@gmail.com
Classifier: Programming Language :: Python :: 3
Classifier: License :: OSI Approved :: Eclipse Public License 2.0 (EPL-2.0)
Classifier: Operating System :: OS Independent
Requires-Python: >=3.7
License-File: LICENSE
Requires-Dist: tensorflow (>=2.5)
Requires-Dist: h5py
Requires-Dist: pysmiles
Requires-Dist: matplotlib
Requires-Dist: scipy
Requires-Dist: tqdm
Requires-Dist: psutil (>=5.6.6)
Requires-Dist: numpy
Requires-Dist: gputil
Requires-Dist: pubchempy
Requires-Dist: PyYAML (>=5.4)
Requires-Dist: scooby
Requires-Dist: sqlalchemy (>=1.4)
Requires-Dist: pandas (>=1.0.0)
Requires-Dist: tensorflow-probability
Requires-Dist: colorutils
Requires-Dist: bokeh
Requires-Dist: chemfiles
Requires-Dist: dot4dict
Requires-Dist: jaxlib
Requires-Dist: jax
